arcade_hubspot_automation_api/__init__.py
arcade_hubspot_automation_api/moar/hubspot_automation.json
arcade_hubspot_automation_api/moar/openapi.json
arcade_hubspot_automation_api/tools/__init__.py
arcade_hubspot_automation_api/tools/request_body_schemas.py
arcade_hubspot_automation_api/wrapper_tools/CheckContactEnrollmentStatus.json
arcade_hubspot_automation_api/wrapper_tools/CompleteActionExecution.json
arcade_hubspot_automation_api/wrapper_tools/CompleteBatchActionExecutions.json
arcade_hubspot_automation_api/wrapper_tools/EnrollContactInSequence.json
arcade_hubspot_automation_api/wrapper_tools/FetchEmailCampaigns.json
arcade_hubspot_automation_api/wrapper_tools/GetSequenceDetails.json
arcade_hubspot_automation_api/wrapper_tools/GetUserSequences.json
arcade_hubspot_automation_api/wrapper_tools/GetWorkflowIdMappings.json
arcade_hubspot_automation_api/wrapper_tools/GetWorkflows.json
arcade_hubspot_automation_api-1.0.0.dist-info/METADATA
arcade_hubspot_automation_api-1.0.0.dist-info/WHEEL
arcade_hubspot_automation_api-1.0.0.dist-info/entry_points.txt
arcade_hubspot_automation_api-1.0.0.dist-info/licenses/LICENSE
arcade_hubspot_automation_api-1.0.0.dist-info/RECORD
